synapse_mcp/__init__.py
synapse_mcp/__main__.py
synapse_mcp/app.py
synapse_mcp/auth_middleware.py
synapse_mcp/connection_auth.py
synapse_mcp/context_helpers.py
synapse_mcp/resources.py
synapse_mcp/server.py
synapse_mcp/tools.py
synapse_mcp/utils.py
synapse_mcp/entities/__init__.py
synapse_mcp/entities/base.py
synapse_mcp/entities/dataset.py
synapse_mcp/entities/file.py
synapse_mcp/entities/folder.py
synapse_mcp/entities/project.py
synapse_mcp/entities/table.py
synapse_mcp/oauth/__init__.py
synapse_mcp/oauth/client_registry.py
synapse_mcp/oauth/config.py
synapse_mcp/oauth/factory.py
synapse_mcp/oauth/jwt.py
synapse_mcp/oauth/proxy.py
synapse_mcp/session_storage/__init__.py
synapse_mcp/session_storage/base.py
synapse_mcp/session_storage/memory.py
synapse_mcp/session_storage/redis_backend.py
iflow_mcp_susheel_synapse_mcp-0.2.0.dist-info/METADATA
iflow_mcp_susheel_synapse_mcp-0.2.0.dist-info/WHEEL
iflow_mcp_susheel_synapse_mcp-0.2.0.dist-info/entry_points.txt
iflow_mcp_susheel_synapse_mcp-0.2.0.dist-info/licenses/LICENSE
iflow_mcp_susheel_synapse_mcp-0.2.0.dist-info/RECORD
