Metadata-Version: 2.4
Name: iflow-mcp_susheel_synapse-mcp
Version: 0.2.0
Summary: A Model Context Protocol (MCP) server that exposes Synapse entities and utilities
Project-URL: Homepage, https://github.com/Sage-Bionetworks/synapse-mcp
Project-URL: Issues, https://github.com/Sage-Bionetworks/synapse-mcp/issues
Author-email: Sage Bionetworks <synapseinfo@sagebase.org>, Susheel Varma <susheel.varma@sagebase.org>, Anh Nguyet Vu <anh.nguyet.vu@sagebase.org>
License: MIT
License-File: LICENSE
Keywords: bioinformatics,mcp,metadata,synapse
Classifier: Development Status :: 4 - Beta
Classifier: Intended Audience :: Science/Research
Classifier: License :: OSI Approved :: MIT License
Classifier: Programming Language :: Python :: 3
Classifier: Programming Language :: Python :: 3.10
Classifier: Programming Language :: Python :: 3.11
Classifier: Topic :: Scientific/Engineering :: Bio-Informatics
Requires-Python: >=3.10
Requires-Dist: cryptography==41.0.0
Requires-Dist: fastmcp==2.12.3
Requires-Dist: pandas==1.5.0
Requires-Dist: pyjwt==2.8.0
Requires-Dist: redis==5.0.0
Requires-Dist: requests==2.32.3
Requires-Dist: synapseclient==4.9.0
